pysimplicityhl-0.3.9.dist-info/METADATA
pysimplicityhl-0.3.9.dist-info/WHEEL
pysimplicityhl-0.3.9.dist-info/licenses/LICENSE
pysimplicityhl/__init__.py
pysimplicityhl/pysimplicityhl.cpython-310-darwin.so
pysimplicityhl-0.3.9.dist-info/RECORD
