Metadata-Version: 2.4
Name: pysimplicityhl
Version: 0.3.9
License-File: LICENSE
Summary: Python module for simplicityhl compiler
Author-email: coremoon <237020170+coremoon@users.noreply.github.com>
Requires-Python: >=3.9
